firefly_widgets/__init__.py
firefly_widgets/_version.py
firefly_widgets/image.py
firefly_widgets/table.py
firefly_widgets/utils.py
firefly_widgets/static/extension.js
firefly_widgets/static/index.js
firefly_widgets/static/index.js.map
firefly_widgets-0.1.0b3.data/data/share/jupyter/nbextensions/jupyter-firefly/extension.js
firefly_widgets-0.1.0b3.data/data/share/jupyter/nbextensions/jupyter-firefly/index.js
firefly_widgets-0.1.0b3.data/data/share/jupyter/nbextensions/jupyter-firefly/index.js.map
firefly_widgets-0.1.0b3.dist-info/DESCRIPTION.rst
firefly_widgets-0.1.0b3.dist-info/METADATA
firefly_widgets-0.1.0b3.dist-info/RECORD
firefly_widgets-0.1.0b3.dist-info/WHEEL
firefly_widgets-0.1.0b3.dist-info/metadata.json
firefly_widgets-0.1.0b3.dist-info/top_level.txt
