Metadata-Version: 2.0
Name: firefly-widgets
Version: 0.1.0b3
Summary: Firefly as Widgets
Home-page: http://jupyter.org
Author: IPAC LSST SUIT
Author-email: shupe@ipac.caltech.edu
License: UNKNOWN
Keywords: ipython,jupyter,widgets
Platform: UNKNOWN
Classifier: Development Status :: 4 - Beta
Classifier: Framework :: IPython
Classifier: Intended Audience :: Developers
Classifier: Intended Audience :: Science/Research
Classifier: Topic :: Multimedia :: Graphics
Classifier: Programming Language :: Python :: 2
Classifier: Programming Language :: Python :: 2.7
Classifier: Programming Language :: Python :: 3
Classifier: Programming Language :: Python :: 3.3
Classifier: Programming Language :: Python :: 3.4
Classifier: Programming Language :: Python :: 3.5
Requires-Dist: astropy (>=1.2.0)
Requires-Dist: ipywidgets (>=6.0.0)
